{
  "students": [
    {
      "id": 1,
      "avatar_url": "https://images.unsplash.com/photo-1505632958218-4f23394784a6?ixlib=rb-1.2.1&ixid=eyJhcHBfaWQiOjEyMDd9&auto=format&fit=crop&w=400&q=80",
      "nome": "José Andrade",
      "email": "julioalvarez22@gmail.com",
      "nascimento": 1093219200000,
      "anoEscolar": "3",
      "cargaHoraria": "120"
    },
    {
      "id": 2,
      "avatar_url": "https://images.unsplash.com/photo-1512413316925-fd4b93f31521?ixlib=rb-1.2.1&ixid=eyJhcHBfaWQiOjEyMDd9&auto=format&fit=crop&w=334&q=80",
      "nome": "Rebecca Lopez",
      "email": "bettyboop@gmail.com",
      "nascimento": 1163289600000,
      "anoEscolar": "2",
      "cargaHoraria": "90"
    },
    {
      "id": 3,
      "avatar_url": "https://images.unsplash.com/photo-1589644366481-1719f9f46e9d?ixlib=rb-1.2.1&ixid=eyJhcHBfaWQiOjEyMDd9&auto=format&fit=crop&w=460&q=80",
      "nome": "Ricardo Andriolli",
      "email": "art_jowjow@gmail.com",
      "nascimento": 1159315200000,
      "anoEscolar": "1",
      "cargaHoraria": "160"
    }
  ],
  "teachers": [
    {
      "id": 1,
      "avatar_url": "https://images.unsplash.com/photo-1561677843-39dee7a319ca?ixlib=rb-1.2.1&ixid=eyJhcHBfaWQiOjEyMDd9&auto=format&fit=crop&w=500&q=60",
      "nome": "Hugo Lopez",
      "nascimento": 556416000000,
      "formacao": "superior",
      "modalidade": "distancia",
      "materias": "geografia, filosofia",
      "created_at": 1588437644309
    },
    {
      "id": 2,
      "avatar_url": "https://images.unsplash.com/photo-1573496799652-408c2ac9fe98?ixlib=rb-1.2.1&ixid=eyJhcHBfaWQiOjEyMDd9&auto=format&fit=crop&w=500&q=60",
      "nome": "Cleide Santos",
      "nascimento": 393206400000,
      "formacao": "mestrado",
      "modalidade": "presencial",
      "materias": " espanhol,francês",
      "created_at": 1588438680538
    },
    {
      "id": 3,
      "avatar_url": "https://images.unsplash.com/photo-1494790108377-be9c29b29330?ixlib=rb-1.2.1&ixid=eyJhcHBfaWQiOjEyMDd9&auto=format&fit=crop&w=500&q=60",
      "nome": "Valerie Black",
      "nascimento": 640396800000,
      "formacao": "doutorado",
      "modalidade": "distancia",
      "materias": "português,literatura",
      "created_at": 1589291400781
    },
    {
      "id": 4,
      "avatar_url": "https://images.unsplash.com/photo-1548449112-96a38a643324?ixlib=rb-1.2.1&ixid=eyJhcHBfaWQiOjEyMDd9&auto=format&fit=crop&w=500&q=60",
      "nome": "Pedro Martins",
      "nascimento": 340416000000,
      "formacao": "mestrado",
      "modalidade": "presencial",
      "materias": "matemática, geometria",
      "created_at": 1589414803791
    }
  ]
}